[
  {
    "message": "@s◆将来に思いを馳せて◆"
  },
  {
    "message": "@s◆将来に思いを馳せて◆"
  },
  {
    "message": "@s◆出合い頭アクシデント◆"
  },
  {
    "message": "@s◆出合い頭アクシデント◆"
  },
  {
    "message": "@s◆我悟りたる◆"
  },
  {
    "message": "@s◆我悟りたる◆"
  },
  {
    "message": "@s◆ひよりからの依頼◆"
  },
  {
    "message": "@s◆ひよりからの依頼◆"
  },
  {
    "message": "@s◆昼食を相席して◆"
  },
  {
    "message": "@s◆昼食を相席して◆"
  },
  {
    "message": "@s◆信頼と真摯◆"
  },
  {
    "message": "@s◆信頼と真摯◆"
  },
  {
    "message": "@s◆３人寄っての◆"
  },
  {
    "message": "@s◆３人寄っての◆"
  },
  {
    "message": "@s◆急ぎ咲かせし恋の花◆"
  },
  {
    "message": "@s◆急ぎ咲かせし恋の花◆"
  },
  {
    "message": "@s◆ひよりの待ち伏せ◆"
  },
  {
    "message": "@s◆ひよりの待ち伏せ◆"
  },
  {
    "message": "@s◆ひよりとお出かけ◆"
  },
  {
    "message": "@s◆ひよりとお出かけ◆"
  },
  {
    "message": "@s◆未羽の相談ごと◆"
  },
  {
    "message": "@s◆未羽の相談ごと◆"
  },
  {
    "message": "@s◆探偵と風紀委員◆"
  },
  {
    "message": "@s◆探偵と風紀委員◆"
  },
  {
    "message": "@s◆改めて勝負を◆"
  },
  {
    "message": "@s◆改めて勝負を◆"
  },
  {
    "message": "@s◆トキメキデート計画◆"
  },
  {
    "message": "@s◆トキメキデート計画◆"
  },
  {
    "message": "@s◆第二ボタンと気持ち◆"
  },
  {
    "message": "@s◆第二ボタンと気持ち◆"
  },
  {
    "message": "@s◆卒業式のその後に◆"
  },
  {
    "message": "@s◆卒業式のその後に◆"
  },
  {
    "message": "@s◆俺はどちらと……◆"
  },
  {
    "message": "@s◆俺はどちらと……◆"
  },
  {
    "message": "@s◆俺の答えは……◆"
  },
  {
    "message": "@s◆俺の答えは……◆"
  },
  {
    "message": "@s◆突然の延長戦宣言！◆"
  },
  {
    "message": "@s◆突然の延長戦宣言！◆"
  },
  {
    "message": "@s◆後悔と迷いと◆"
  },
  {
    "message": "@s◆後悔と迷いと◆"
  },
  {
    "message": "@s◆ひよりからの事情聴取◆"
  },
  {
    "message": "@s◆ひよりからの事情聴取◆"
  },
  {
    "message": "@s◆オールインワンで勝負◆"
  },
  {
    "message": "@s◆オールインワンで勝負◆"
  },
  {
    "message": "@s◆一登の心が動く時は？◆"
  },
  {
    "message": "@s◆一登の心が動く時は？◆"
  },
  {
    "message": "@s◆ひよりのいじりポイント◆"
  },
  {
    "message": "@s◆ひよりのいじりポイント◆"
  },
  {
    "message": "@s◆ひより天啓を得る◆"
  },
  {
    "message": "@s◆ひより天啓を得る◆"
  },
  {
    "message": "@s◆サプライズな計画◆"
  },
  {
    "message": "@s◆サプライズな計画◆"
  },
  {
    "message": "@s◆決着はプールで！◆"
  },
  {
    "message": "@s◆決着はプールで！◆"
  },
  {
    "message": "@s◆ついてくるつもり？◆"
  },
  {
    "message": "@s◆ついてくるつもり？◆"
  },
  {
    "message": "@s◆ちょっとした優越感◆"
  },
  {
    "message": "@s◆ちょっとした優越感◆"
  },
  {
    "message": "@s◆いよいよ明日◆"
  },
  {
    "message": "@s◆いよいよ明日◆"
  },
  {
    "message": "@s◆友情と恋愛の線引き◆"
  },
  {
    "message": "@s◆友情と恋愛の線引き◆"
  },
  {
    "message": "@s◆いざ小旅行へ出発◆"
  },
  {
    "message": "@s◆いざ小旅行へ出発◆"
  },
  {
    "message": "@s◆他言無用な出会い◆"
  },
  {
    "message": "@s◆他言無用な出会い◆"
  },
  {
    "message": "@s◆キミがわからない◆"
  },
  {
    "message": "@s◆キミがわからない◆"
  },
  {
    "message": "@s◆未羽のアピール・デイ◆"
  },
  {
    "message": "@s◆未羽のアピール・デイ◆"
  },
  {
    "message": "@s◆翻弄するひより◆"
  },
  {
    "message": "@s◆翻弄するひより◆"
  },
  {
    "message": "@s◆本校でもムササビ女子◆"
  },
  {
    "message": "@s◆本校でもムササビ女子◆"
  },
  {
    "message": "@s◆相手に寄り添ったこと◆"
  },
  {
    "message": "@s◆相手に寄り添ったこと◆"
  },
  {
    "message": "@s◆ひより、手こずる◆"
  },
  {
    "message": "@s◆ひより、手こずる◆"
  },
  {
    "message": "@s◆キャッチ・ザ・ひより◆"
  },
  {
    "message": "@s◆キャッチ・ザ・ひより◆"
  },
  {
    "message": "@s◆まだ、でも、もう少し◆"
  },
  {
    "message": "@s◆まだ、でも、もう少し◆"
  },
  {
    "message": "@s◆ひよりのため◆"
  },
  {
    "message": "@s◆ひよりのため◆"
  },
  {
    "message": "@s◆私には止められない◆"
  },
  {
    "message": "@s◆私には止められない◆"
  },
  {
    "message": "@s◆私が止めなくちゃ◆"
  },
  {
    "message": "@s◆私が止めなくちゃ◆"
  },
  {
    "message": "@s◆ひよりの初恋◆"
  },
  {
    "message": "@s◆ひよりの初恋◆"
  },
  {
    "message": "@s◆破られた１００％記録◆"
  },
  {
    "message": "@s◆破られた１００％記録◆"
  },
  {
    "message": "@s◆妖精舞う月夜に◆"
  },
  {
    "message": "@s◆妖精舞う月夜に◆"
  },
  {
    "message": "@s◆先日のことは忘れて◆"
  },
  {
    "message": "@s◆先日のことは忘れて◆"
  },
  {
    "message": "@s◆ＳＳＲみんなでフォロー◆"
  },
  {
    "message": "@s◆ＳＳＲみんなでフォロー◆"
  },
  {
    "message": "@s◆ひよりを蝕むもの◆"
  },
  {
    "message": "@s◆ひよりを蝕むもの◆"
  },
  {
    "message": "@s◆恋愛請負は廃業◆"
  },
  {
    "message": "@s◆恋愛請負は廃業◆"
  },
  {
    "message": "@s◆ひよりちゃんを助けて◆"
  },
  {
    "message": "@s◆ひよりちゃんを助けて◆"
  },
  {
    "message": "@s◆神様からの贈り物◆"
  },
  {
    "message": "@s◆神様からの贈り物◆"
  },
  {
    "message": "@s◆俺にできることを◆"
  },
  {
    "message": "@s◆俺にできることを◆"
  },
  {
    "message": "@s◆琴里の後押し◆"
  },
  {
    "message": "@s◆琴里の後押し◆"
  },
  {
    "message": "@s◆フラグより見るべきもの◆"
  },
  {
    "message": "@s◆フラグより見るべきもの◆"
  },
  {
    "message": "@s◆つけるべきケジメ◆"
  },
  {
    "message": "@s◆つけるべきケジメ◆"
  },
  {
    "message": "@s◆実家へＧＯ！◆"
  },
  {
    "message": "@s◆実家へＧＯ！◆"
  },
  {
    "message": "@s◆お家デートだね◆"
  },
  {
    "message": "@s◆お家デートだね◆"
  },
  {
    "message": "@s◆楽しきことの予兆◆"
  },
  {
    "message": "@s◆楽しきことの予兆◆"
  },
  {
    "message": "@s◆自重も必要！◆"
  },
  {
    "message": "@s◆自重も必要！◆"
  }
]